hivepepebot/__init__.py
hivepepebot/hivepepebot.py
hivepepebot-0.0.1.dist-info/LICENSE
hivepepebot-0.0.1.dist-info/METADATA
hivepepebot-0.0.1.dist-info/WHEEL
hivepepebot-0.0.1.dist-info/top_level.txt
hivepepebot-0.0.1.dist-info/RECORD
