Metadata-Version: 2.1
Name: hivepepebot
Version: 0.0.1
Summary: A script to find and react to !PEPE commands in comments
Home-page: https://github.com/flaxz/hivepepebot
Author: Erik Gustafsson and Hive Pizza Team
Author-email: erikegse@gmail.com
Project-URL: Bug Tracker, https://github.com/flaxz/hivepepebot/issues
Classifier: Programming Language :: Python :: 3
Classifier: License :: OSI Approved :: MIT License
Classifier: Operating System :: OS Independent
Requires-Python: >=3.6
License-File: LICENSE
